pyrgraph
