Metadata-Version: 1.0
Name: pyrgraph
Version: 0.1.2
Summary: Pyrgraph is a Redis-backed graph database
Home-page: http://github.com/alireza-m/pyrgraph
Author: Alireza Meskin
Author-email: alireza.meskin@gmail.com
License: MIT
Platform: UNKNOWN
